bcd2disp.v
`timescale 1ns / 1ps
module bcd2sevenseg(
    input [3:0] bcd,
    output reg [6:0] seg
    );
always @(bcd)
begin
    case (bcd)
        0 : seg = 7'b1111110;
        1 : seg = 7'b0110000;
        2 : seg = 7'b1101101;
        3 : seg = 7'b1111001;
        4 : seg = 7'b0110011;
        5 : seg = 7'b1011011;
        6 : seg = 7'b1011111;
        7 : seg = 7'b1110000;
        8 : seg = 7'b1111111;
        9 : seg = 7'b1111011;
        10 : seg = 7'b1110111;
        11 : seg = 7'b0011111;
        12 : seg = 7'b1001110;
        13 : seg = 7'b0111101;
        14 : seg = 7'b1001111;
        15 : seg = 7'b1000111;
        default : seg = 7'b0000000; 
    endcase
end  
endmodule

register8.v
`timescale 1ns/1ps
module register8(input clk, input [7:0] D, input EI, output reg [7:0] Q);
wire CLK;
assign CLK=(clk & EI);
always @(posedge CLK)
begin
    Q <= D;
end
endmodule

IC.v
`timescale 1ns/1ps
module IC(input clk, input enable, input [3:0] Instruction, output reg [14:0] ctrl_wrd);
wire CLK;
reg [3:0] instr;
assign CLK = (~clk & enable);
reg [2:0] Inst_count;
reg reset_in;

initial begin
    Inst_count <= 3'b111;
    reset_in <= 0;
end
always @ (posedge CLK)
    begin
        Inst_count = reset_in ? 3'b000 : Inst_count+1;
        reset_in = 1'b0;
        case(Inst_count)//HLT, MI, RI, RO, IO, II, AI, AO, SO, SU, BI, OI, CE, CO, J;
            3'b000: ctrl_wrd = 15'b010000000000010;
            3'b001: ctrl_wrd = 15'b000101000000100;
            3'b010: begin
                    case(instr)
                    4'b0001: ctrl_wrd = 15'b010010000000000; // LDA
                    4'b0010: ctrl_wrd = 15'b010010000000000; //ADD
                    4'b0011: ctrl_wrd = 15'b010010000000000;  //SUBT
                    4'b1110: ctrl_wrd = 15'b000000010001000; // OUT
                    4'b0100: ctrl_wrd = 15'b000010000000001; // JMP
                    4'b1111: ctrl_wrd = 15'b100000000000000; // HLT
                    default: ctrl_wrd = 15'b000000000000000;
                    endcase 
                    end      
            3'b011: begin
                    case(instr)
                    4'b0001: ctrl_wrd = 15'b000100100000000; // LDA
                    4'b0010: ctrl_wrd = 15'b000100000010000; //ADD
                    4'b0011: ctrl_wrd = 15'b000100000010000; //SUBT
                    4'b1110: ctrl_wrd = 15'b000000000000000; // OUT
                    4'b0100: ctrl_wrd = 15'b000000000000000; // JMP
                    4'b1111: ctrl_wrd = 15'b000000000000000; // HLT
                    default: ctrl_wrd = 15'b000000000000000;
                    endcase             
                    end
            3'b100: begin
                    case(instr)
                    4'b0001: ctrl_wrd = 15'b000000000000000; // LDA done
                    4'b0010: ctrl_wrd = 15'b000000101000000; //ADD
                    4'b0011: ctrl_wrd = 15'b000000101100000; //SUBT
                    4'b1110: ctrl_wrd = 15'b000000000000000; // OUT
                    4'b0100: ctrl_wrd = 15'b000000000000000; // JMP
                    4'b1111: ctrl_wrd = 15'b000000000000000; // HLT
                    default: ctrl_wrd = 15'b000000000000000;
                    endcase 
                    reset_in = 1'b1; // Have some doubt here..... Maybe this part can go wrong .....
                    end                  
            default: ctrl_wrd = 15'b000000000000000;
        endcase                          
    end


    always @(Instruction)
    begin
        if(Instruction != 4'b0000)
        begin
            instr <= Instruction;
        end
    end

endmodule

tristateBuff.v
`timescale 1ns/1ps
module tristateBuff(input [7:0] data, input enable, output [7:0] dataOut);
    assign dataOut = enable ? data : 8'bzzzzzzzz;
endmodule

RAM.v
`timescale 1ns/1ps
module RAM(input clk, input [3:0] address, input [7:0] data_in, input write_enable, input reset, output reg [7:0] data_out);
reg [7:0] Memory[15:0];
integer i;

initial begin
    Memory[0] = 8'b0001_1001;
    Memory[1] = 8'b0010_1010;
    Memory[2] = 8'b0100_0111;
    Memory[3] = 8'b0011_1011;
    Memory[4] = 8'b0010_1100;
    Memory[5] = 8'b1110_0000;
    Memory[6] = 8'b0001_1101;
    Memory[7] = 8'b1110_0000;
    Memory[8] = 8'b1111_0000;
    Memory[9] = 8'b0000_0011;
    Memory[10] = 8'b0000_0010;
    Memory[11] = 8'b0000_0001;
    Memory[12] = 8'b0000_0101;
    Memory[13] = 8'b0000_1010;
    Memory[14] = 8'b0000_0000;
    Memory[15] = 8'b0000_0000;
end


always @(posedge clk)
begin
    if(!reset)
    begin
        if(write_enable)
        begin
            Memory[address] <= data_in;
        end
        else
        begin
            data_out <= Memory[address];
        end
    end
    else
    begin
        for(i=0;i<=15;i=i+1)
        begin
            Memory[i] <= 0;
        end
    end
end
endmodule

register4.v
`timescale 1ns/1ps
module register4(input clk, input [3:0] D, input EI, output reg [3:0] Q);
wire CLK;
assign CLK=(clk & EI);
always @(posedge CLK)
begin
    Q <= D;
end
endmodule

triBuff4.v
`timescale 1ns/1ps
module triBuff4(input [3:0] data, input enable, output [3:0] dataOut);
    assign dataOut = enable ? data : 4'bzzzz;
endmodule

PC.v
`timescale 1ns/1ps
module PC(input clk, input rst, input enable, input [3:0] jmploc, input jmp, output reg [3:0] count);
wire CLK;
assign CLK = (clk & enable);
initial begin
    count <= 4'b0000;
end
always @(posedge CLK)
begin
    if(rst)
    begin
        count <= 4'b0000;
    end
    else
    begin
        count <= count + 1;
    end
end

always @(posedge clk)
begin
    if(jmp)
    begin
        count <= jmploc;
    end
end
endmodule

ALU.v
`timescale 1ns/1ps
module ALU(input op, input [7:0] A, input [7:0] B, output [8:0] res);
assign res[8:0] = op ? (A[7:0] - B[7:0]) : (A[7:0] + B[7:0]);
endmodule

CPU.v
`timescale 1ns/1ps
`include "ALU.v"
`include "PC.v"
`include "IC.v"
`include "register8.v"
`include "register4.v"
`include "tristateBuff.v"
`include "triBuff4.v"
`include "RAM.v"
`include "bcd2disp.v"

module CPU(input clkin, output [7:0] OutPut, output [6:0] LED1, output [6:0] LED2);
wire [7:0] bus;
wire [3:0] MemAddr;
wire [7:0] Aout;
wire [7:0] Bout;
wire [7:0] Instout;
wire [3:0] Pcount;
wire [3:0] Addr_in;
wire [7:0] Dispout;
wire [7:0] ramOut;
wire [7:0] aluOut;
wire HLT, MI, RI, RO, IO, II, AI, AO, SO, SU, BI, OI, CE, CO, J;
wire PCrst, flag;


assign clk = (clkin & ~HLT);


register8 A(.clk(clk), .D(bus), .Q(Aout), .EI(AI));
tristateBuff triA(.data(Aout), .dataOut(bus), .enable(AO));

register8 B(.clk(clk), .D(bus), .Q(Bout), .EI(BI));

register8 InstReg(.clk(clk), .D(bus), .Q(Instout), .EI(II));
tristateBuff triInstReg(.data(Instout), .dataOut(bus), .enable(IO));

ALU alu(.A(Aout), .B(Bout), .op(SU), .res({flag,aluOut}));
tristateBuff tri_alu(.data(aluOut), .enable(SO), .dataOut(bus));


PC pc(.clk(clk), .rst(1'b0), .enable(CE), .jmp(J), .jmploc(bus[3:0]), .count(Pcount));
triBuff4 tripc(.data(Pcount), .dataOut(bus[3:0]), .enable(CO));



register4 MemAdd(.clk(clk), .D(bus[3:0]), .Q(Addr_in), .EI(MI));

RAM ram(.clk(~clk), .address(Addr_in), .data_in(bus), .write_enable(RI), .reset(1'b0), .data_out(ramOut));
tristateBuff triRam(.data(ramOut), .enable(RO), .dataOut(bus));

IC ic(.clk(clk), .enable(1'b1), .Instruction(bus[7:4]), .ctrl_wrd({HLT, MI, RI, RO, IO, II, AI, AO, SO, SU, BI, OI, CE, CO, J}));

register8 O(.clk(clk), .D(bus), .Q(OutPut), .EI(OI));

bcd2sevenseg seg0(.bcd(OutPut[3:0]), .seg(LED1));
bcd2sevenseg seg1(.bcd(OutPut[7:4]), .seg(LED2));

endmodule

CPU_tb.v
`timescale 1ns/1ps
`include "CPU.v"
module CPUtb();
reg clk;
wire [7:0] outPut;
wire [6:0] LED1;
wire [6:0] LED2;

initial begin
    clk <= 0;
    forever begin
        #10;
        clk <= ~clk;
    end
end

CPU cpu(.clkin(clk), .OutPut(outPut), .LED1(LED1), .LED2(LED2));

initial begin
    $dumpfile("dump.vcd");
    $dumpvars(0, CPUtb);
    #1000;
    $finish;
end

endmodule

outputFiles/dump.vcd
$date
	Tue Jan 21 13:52:56 2020
$end
$version
	Icarus Verilog
$end
$timescale
	1ps
$end
$scope module CPUtb $end
$var wire 8 ! outPut [7:0] $end
$var wire 7 " LED2 [6:0] $end
$var wire 7 # LED1 [6:0] $end
$var reg 1 $ clk $end
$scope module cpu $end
$var wire 8 % bus [7:0] $end
$var wire 1 & clk $end
$var wire 1 $ clkin $end
$var wire 8 ' ramOut [7:0] $end
$var wire 1 ( flag $end
$var wire 8 ) aluOut [7:0] $end
$var wire 1 * SU $end
$var wire 1 + SO $end
$var wire 1 , RO $end
$var wire 1 - RI $end
$var wire 4 . Pcount [3:0] $end
$var wire 8 / OutPut [7:0] $end
$var wire 1 0 OI $end
$var wire 1 1 MI $end
$var wire 7 2 LED2 [6:0] $end
$var wire 7 3 LED1 [6:0] $end
$var wire 1 4 J $end
$var wire 8 5 Instout [7:0] $end
$var wire 1 6 IO $end
$var wire 1 7 II $end
$var wire 1 8 HLT $end
$var wire 1 9 CO $end
$var wire 1 : CE $end
$var wire 8 ; Bout [7:0] $end
$var wire 1 < BI $end
$var wire 8 = Aout [7:0] $end
$var wire 4 > Addr_in [3:0] $end
$var wire 1 ? AO $end
$var wire 1 @ AI $end
$scope module A $end
$var wire 1 A CLK $end
$var wire 8 B D [7:0] $end
$var wire 1 @ EI $end
$var wire 1 & clk $end
$var reg 8 C Q [7:0] $end
$upscope $end
$scope module B $end
$var wire 1 D CLK $end
$var wire 8 E D [7:0] $end
$var wire 1 < EI $end
$var wire 1 & clk $end
$var reg 8 F Q [7:0] $end
$upscope $end
$scope module InstReg $end
$var wire 1 G CLK $end
$var wire 8 H D [7:0] $end
$var wire 1 7 EI $end
$var wire 1 & clk $end
$var reg 8 I Q [7:0] $end
$upscope $end
$scope module MemAdd $end
$var wire 1 J CLK $end
$var wire 4 K D [3:0] $end
$var wire 1 1 EI $end
$var wire 1 & clk $end
$var reg 4 L Q [3:0] $end
$upscope $end
$scope module O $end
$var wire 1 M CLK $end
$var wire 8 N D [7:0] $end
$var wire 1 0 EI $end
$var wire 1 & clk $end
$var reg 8 O Q [7:0] $end
$upscope $end
$scope module alu $end
$var wire 8 P A [7:0] $end
$var wire 8 Q B [7:0] $end
$var wire 1 * op $end
$var wire 9 R res [8:0] $end
$upscope $end
$scope module ic $end
$var wire 1 S CLK $end
$var wire 4 T Instruction [3:0] $end
$var wire 1 & clk $end
$var wire 1 U enable $end
$var reg 3 V Inst_count [2:0] $end
$var reg 15 W ctrl_wrd [14:0] $end
$var reg 4 X instr [3:0] $end
$var reg 1 Y reset_in $end
$upscope $end
$scope module pc $end
$var wire 1 Z CLK $end
$var wire 1 & clk $end
$var wire 1 : enable $end
$var wire 1 4 jmp $end
$var wire 4 [ jmploc [3:0] $end
$var wire 1 \ rst $end
$var reg 4 ] count [3:0] $end
$upscope $end
$scope module ram $end
$var wire 4 ^ address [3:0] $end
$var wire 1 _ clk $end
$var wire 8 ` data_in [7:0] $end
$var wire 1 a reset $end
$var wire 1 - write_enable $end
$var reg 8 b data_out [7:0] $end
$var integer 32 c i [31:0] $end
$upscope $end
$scope module seg0 $end
$var wire 4 d bcd [3:0] $end
$var reg 7 e seg [6:0] $end
$upscope $end
$scope module seg1 $end
$var wire 4 f bcd [3:0] $end
$var reg 7 g seg [6:0] $end
$upscope $end
$scope module triA $end
$var wire 8 h data [7:0] $end
$var wire 8 i dataOut [7:0] $end
$var wire 1 ? enable $end
$upscope $end
$scope module triInstReg $end
$var wire 8 j data [7:0] $end
$var wire 8 k dataOut [7:0] $end
$var wire 1 6 enable $end
$upscope $end
$scope module triRam $end
$var wire 8 l data [7:0] $end
$var wire 8 m dataOut [7:0] $end
$var wire 1 , enable $end
$upscope $end
$scope module tri_alu $end
$var wire 8 n data [7:0] $end
$var wire 8 o dataOut [7:0] $end
$var wire 1 + enable $end
$upscope $end
$scope module tripc $end
$var wire 4 p data [3:0] $end
$var wire 1 9 enable $end
$var wire 4 q dataOut [3:0] $end
$upscope $end
$upscope $end
$upscope $end
$enddefinitions $end
#0
$dumpvars
b0 q
b0 p
bz0000 o
bx n
bz0000 m
bx l
bz0000 k
bx j
bz0000 i
bx h
bx g
bx f
bx e
bx d
bx c
bx b
0a
bz0000 `
1_
bx ^
b0 ]
0\
b0 [
0Z
0Y
bx X
b10000000000010 W
b0 V
1U
bz T
1S
bx R
bx Q
bx P
bx O
bz0000 N
0M
bx L
b0 K
0J
bx I
bz0000 H
0G
bx F
bz0000 E
0D
bx C
bz0000 B
0A
0@
0?
bx >
bx =
0<
bx ;
0:
19
08
07
06
bx 5
04
bx 3
bx 2
11
00
bx /
b0 .
0-
0,
0+
0*
bx )
x(
bx '
0&
bz0000 %
0$
bx #
bx "
bx !
$end
#10000
b0 >
b0 L
b0 ^
0S
0_
1J
1&
1$
#20000
b1 X
b11010 '
b11010 b
b11010 l
b1010 [
b1010 K
b1 T
bz q
b11010 %
b11010 B
b11010 E
b11010 H
b11010 N
b11010 `
b11010 i
b11010 k
b11010 m
b11010 o
09
1:
17
1,
01
b101000000100 W
b1 V
1S
1_
0J
0&
0$
#30000
b11010 5
b11010 I
b11010 j
b1 .
b1 ]
b1 p
0S
0_
1G
1Z
1&
1$
#40000
b11010 %
b11010 B
b11010 E
b11010 H
b11010 N
b11010 `
b11010 i
b11010 k
b11010 m
b11010 o
0:
07
16
0,
11
b10010000000000 W
b10 V
1S
1_
0G
0Z
0&
0$
#50000
b1010 >
b1010 L
b1010 ^
0S
0_
1J
1&
1$
#60000
b11 [
b11 K
b0 T
b11 %
b11 B
b11 E
b11 H
b11 N
b11 `
b11 i
b11 k
b11 m
b11 o
b11 '
b11 b
b11 l
1@
06
1,
01
b100100000000 W
b11 V
1S
1_
0J
0&
0$
#70000
b11 =
b11 C
b11 P
b11 h
0S
0_
1A
1&
1$
#80000
bz [
bz K
bz T
bz %
bz B
bz E
bz H
bz N
bz `
bz i
bz k
bz m
bz o
0@
0,
1Y
b0 W
b100 V
1S
1_
0A
0&
0$
#90000
0S
0_
1&
1$
#100000
b1 [
b1 K
bz0001 %
bz0001 B
bz0001 E
bz0001 H
bz0001 N
bz0001 `
bz0001 i
bz0001 k
bz0001 m
bz0001 o
b1 q
19
11
b10000000000010 W
0Y
b0 V
1S
1_
0&
0$
#110000
b1 >
b1 L
b1 ^
0S
0_
1J
1&
1$
#120000
b10 X
b101011 '
b101011 b
b101011 l
b1011 [
b1011 K
b10 T
bz q
b101011 %
b101011 B
b101011 E
b101011 H
b101011 N
b101011 `
b101011 i
b101011 k
b101011 m
b101011 o
09
1:
17
1,
01
b101000000100 W
b1 V
1S
1_
0J
0&
0$
#130000
b101011 5
b101011 I
b101011 j
b10 .
b10 ]
b10 p
0S
0_
1G
1Z
1&
1$
#140000
b101011 %
b101011 B
b101011 E
b101011 H
b101011 N
b101011 `
b101011 i
b101011 k
b101011 m
b101011 o
0:
07
16
0,
11
b10010000000000 W
b10 V
1S
1_
0G
0Z
0&
0$
#150000
b1011 >
b1011 L
b1011 ^
0S
0_
1J
1&
1$
#160000
b10 [
b10 K
b0 T
b10 %
b10 B
b10 E
b10 H
b10 N
b10 `
b10 i
b10 k
b10 m
b10 o
b10 '
b10 b
b10 l
1<
06
1,
01
b100000010000 W
b11 V
1S
1_
0J
0&
0$
#170000
b101 )
b101 n
0(
b101 R
b10 ;
b10 F
b10 Q
0S
0_
1D
1&
1$
#180000
b101 [
b101 K
b101 %
b101 B
b101 E
b101 H
b101 N
b101 `
b101 i
b101 k
b101 m
b101 o
0<
1+
1@
0,
1Y
b101000000 W
b100 V
1S
1_
0D
0&
0$
#190000
b111 [
b111 K
b111 %
b111 B
b111 E
b111 H
b111 N
b111 `
b111 i
b111 k
b111 m
b111 o
b111 )
b111 n
b111 R
b101 =
b101 C
b101 P
b101 h
0S
0_
1A
1&
1$
#200000
b10 [
b10 K
bz T
b10 q
bz0010 %
bz0010 B
bz0010 E
bz0010 H
bz0010 N
bz0010 `
bz0010 i
bz0010 k
bz0010 m
bz0010 o
19
0+
0@
11
b10000000000010 W
0Y
b0 V
1S
1_
0A
0&
0$
#210000
b10 >
b10 L
b10 ^
0S
0_
1J
1&
1$
#220000
b100 X
b110 [
b110 K
b1000110 '
b1000110 b
b1000110 l
b100 T
bz q
b1000110 %
b1000110 B
b1000110 E
b1000110 H
b1000110 N
b1000110 `
b1000110 i
b1000110 k
b1000110 m
b1000110 o
09
1:
17
1,
01
b101000000100 W
b1 V
1S
1_
0J
0&
0$
#230000
b1000110 5
b1000110 I
b1000110 j
b11 .
b11 ]
b11 p
0S
0_
1G
1Z
1&
1$
#240000
b1000110 %
b1000110 B
b1000110 E
b1000110 H
b1000110 N
b1000110 `
b1000110 i
b1000110 k
b1000110 m
b1000110 o
14
0:
07
16
0,
b10000000001 W
b10 V
1S
1_
0G
0Z
0&
0$
#250000
b110 .
b110 ]
b110 p
0S
0_
1&
1$
#260000
bz [
bz K
bz T
bz %
bz B
bz E
bz H
bz N
bz `
bz i
bz k
bz m
bz o
04
06
b0 W
b11 V
1S
1_
0&
0$
#270000
0S
0_
1&
1$
#280000
1Y
b100 V
1S
1_
0&
0$
#290000
0S
0_
1&
1$
#300000
b110 [
b110 K
bz0110 %
bz0110 B
bz0110 E
bz0110 H
bz0110 N
bz0110 `
bz0110 i
bz0110 k
bz0110 m
bz0110 o
b110 q
19
11
b10000000000010 W
0Y
b0 V
1S
1_
0&
0$
#310000
b110 >
b110 L
b110 ^
0S
0_
1J
1&
1$
#320000
b1 X
b1110 [
b1110 K
b11110 '
b11110 b
b11110 l
b1 T
bz q
b11110 %
b11110 B
b11110 E
b11110 H
b11110 N
b11110 `
b11110 i
b11110 k
b11110 m
b11110 o
09
1:
17
1,
01
b101000000100 W
b1 V
1S
1_
0J
0&
0$
#330000
b11110 5
b11110 I
b11110 j
b111 .
b111 ]
b111 p
0S
0_
1G
1Z
1&
1$
#340000
b11110 %
b11110 B
b11110 E
b11110 H
b11110 N
b11110 `
b11110 i
b11110 k
b11110 m
b11110 o
0:
07
16
0,
11
b10010000000000 W
b10 V
1S
1_
0G
0Z
0&
0$
#350000
b1110 >
b1110 L
b1110 ^
0S
0_
1J
1&
1$
#360000
b1010 [
b1010 K
b0 T
b1010 %
b1010 B
b1010 E
b1010 H
b1010 N
b1010 `
b1010 i
b1010 k
b1010 m
b1010 o
b1010 '
b1010 b
b1010 l
1@
06
1,
01
b100100000000 W
b11 V
1S
1_
0J
0&
0$
#370000
b1100 )
b1100 n
b1100 R
b1010 =
b1010 C
b1010 P
b1010 h
0S
0_
1A
1&
1$
#380000
bz [
bz K
bz T
bz %
bz B
bz E
bz H
bz N
bz `
bz i
bz k
bz m
bz o
0@
0,
1Y
b0 W
b100 V
1S
1_
0A
0&
0$
#390000
0S
0_
1&
1$
#400000
b111 [
b111 K
bz0111 %
bz0111 B
bz0111 E
bz0111 H
bz0111 N
bz0111 `
bz0111 i
bz0111 k
bz0111 m
bz0111 o
b111 q
19
11
b10000000000010 W
0Y
b0 V
1S
1_
0&
0$
#410000
b111 >
b111 L
b111 ^
0S
0_
1J
1&
1$
#420000
b10 X
b101111 '
b101111 b
b101111 l
b1111 [
b1111 K
b10 T
bz q
b101111 %
b101111 B
b101111 E
b101111 H
b101111 N
b101111 `
b101111 i
b101111 k
b101111 m
b101111 o
09
1:
17
1,
01
b101000000100 W
b1 V
1S
1_
0J
0&
0$
#430000
b101111 5
b101111 I
b101111 j
b1000 .
b1000 ]
b1000 p
0S
0_
1G
1Z
1&
1$
#440000
b101111 %
b101111 B
b101111 E
b101111 H
b101111 N
b101111 `
b101111 i
b101111 k
b101111 m
b101111 o
0:
07
16
0,
11
b10010000000000 W
b10 V
1S
1_
0G
0Z
0&
0$
#450000
b1111 >
b1111 L
b1111 ^
0S
0_
1J
1&
1$
#460000
b1011 [
b1011 K
b0 T
b1011 %
b1011 B
b1011 E
b1011 H
b1011 N
b1011 `
b1011 i
b1011 k
b1011 m
b1011 o
b1011 '
b1011 b
b1011 l
1<
06
1,
01
b100000010000 W
b11 V
1S
1_
0J
0&
0$
#470000
b10101 )
b10101 n
b10101 R
b1011 ;
b1011 F
b1011 Q
0S
0_
1D
1&
1$
#480000
b1 X
b101 [
b101 K
b1 T
b10101 %
b10101 B
b10101 E
b10101 H
b10101 N
b10101 `
b10101 i
b10101 k
b10101 m
b10101 o
0<
1+
1@
0,
1Y
b101000000 W
b100 V
1S
1_
0D
0&
0$
#490000
b10 X
b0 [
b0 K
b10 T
b100000 %
b100000 B
b100000 E
b100000 H
b100000 N
b100000 `
b100000 i
b100000 k
b100000 m
b100000 o
b100000 )
b100000 n
b100000 R
b10101 =
b10101 C
b10101 P
b10101 h
0S
0_
1A
1&
1$
#500000
b1000 [
b1000 K
bz T
b1000 q
bz1000 %
bz1000 B
bz1000 E
bz1000 H
bz1000 N
bz1000 `
bz1000 i
bz1000 k
bz1000 m
bz1000 o
19
0+
0@
11
b10000000000010 W
0Y
b0 V
1S
1_
0A
0&
0$
#510000
b1000 >
b1000 L
b1000 ^
0S
0_
1J
1&
1$
#520000
b1110 X
b11100000 '
b11100000 b
b11100000 l
b0 [
b0 K
b1110 T
bz q
b11100000 %
b11100000 B
b11100000 E
b11100000 H
b11100000 N
b11100000 `
b11100000 i
b11100000 k
b11100000 m
b11100000 o
09
1:
17
1,
01
b101000000100 W
b1 V
1S
1_
0J
0&
0$
#530000
b11100000 5
b11100000 I
b11100000 j
b1001 .
b1001 ]
b1001 p
0S
0_
1G
1Z
1&
1$
#540000
b1 X
b101 [
b101 K
b1 T
b10101 %
b10101 B
b10101 E
b10101 H
b10101 N
b10101 `
b10101 i
b10101 k
b10101 m
b10101 o
0:
10
1?
07
0,
b10001000 W
b10 V
1S
1_
0G
0Z
0&
0$
#550000
b110000 "
b110000 2
b110000 g
b1011011 #
b1011011 3
b1011011 e
b1 f
b101 d
b10101 !
b10101 /
b10101 O
0S
0_
1M
1&
1$
#560000
b1110 X
b0 [
b0 K
b1110 T
b11100000 %
b11100000 B
b11100000 E
b11100000 H
b11100000 N
b11100000 `
b11100000 i
b11100000 k
b11100000 m
b11100000 o
00
0?
1@
1,
b100100000000 W
b11 V
1S
1_
0M
0&
0$
#570000
b11101011 )
b11101011 n
b11101011 R
b11100000 =
b11100000 C
b11100000 P
b11100000 h
0S
0_
1A
1&
1$
#580000
bz [
bz K
bz T
bz %
bz B
bz E
bz H
bz N
bz `
bz i
bz k
bz m
bz o
0@
0,
1Y
b0 W
b100 V
1S
1_
0A
0&
0$
#590000
0S
0_
1&
1$
#600000
b1001 [
b1001 K
bz1001 %
bz1001 B
bz1001 E
bz1001 H
bz1001 N
bz1001 `
bz1001 i
bz1001 k
bz1001 m
bz1001 o
b1001 q
19
11
b10000000000010 W
0Y
b0 V
1S
1_
0&
0$
#610000
b1001 >
b1001 L
b1001 ^
0S
0_
1J
1&
1$
#620000
b1111 X
b11110000 '
b11110000 b
b11110000 l
b0 [
b0 K
b1111 T
bz q
b11110000 %
b11110000 B
b11110000 E
b11110000 H
b11110000 N
b11110000 `
b11110000 i
b11110000 k
b11110000 m
b11110000 o
09
1:
17
1,
01
b101000000100 W
b1 V
1S
1_
0J
0&
0$
#630000
b11110000 5
b11110000 I
b11110000 j
b1010 .
b1010 ]
b1010 p
0S
0_
1G
1Z
1&
1$
#640000
bz [
bz K
bz T
bz %
bz B
bz E
bz H
bz N
bz `
bz i
bz k
bz m
bz o
0:
07
0,
18
b100000000000000 W
b10 V
1S
1_
0G
0Z
0&
0$
